pigeonsai/__init__.py
pigeonsai/_client.py
pigeonsai/_constants.py
pigeonsai/_exceptions.py
pigeonsai/_utils/__init__.py
pigeonsai/_utils/_utils.py
pigeonsai/resources/__init__.py
pigeonsai/resources/anomaly_detector.py
pigeonsai/resources/data_connector.py
pigeonsai/resources/recommender.py
pigeonsai-1.0.8.dist-info/METADATA
pigeonsai-1.0.8.dist-info/WHEEL
pigeonsai-1.0.8.dist-info/top_level.txt
pigeonsai-1.0.8.dist-info/RECORD
